pycrystalpay/__init__.py
pycrystalpay/exceptions.py
pycrystalpay/types/__init__.py
pycrystalpay/types/balance.py
pycrystalpay/types/invoice.py
pycrystalpay/types/me.py
pycrystalpay/types/method.py
pycrystalpay/types/payoff.py
pycrystalpay/wrapper/__init__.py
pycrystalpay/wrapper/async_/__init__.py
pycrystalpay/wrapper/async_/async_client.py
pycrystalpay/wrapper/async_/balance.py
pycrystalpay/wrapper/async_/base.py
pycrystalpay/wrapper/async_/invoice.py
pycrystalpay/wrapper/async_/me.py
pycrystalpay/wrapper/async_/method.py
pycrystalpay/wrapper/async_/payoff.py
pycrystalpay-0.0.2.dist-info/LICENSE
pycrystalpay-0.0.2.dist-info/METADATA
pycrystalpay-0.0.2.dist-info/WHEEL
pycrystalpay-0.0.2.dist-info/top_level.txt
pycrystalpay-0.0.2.dist-info/RECORD
