Metadata-Version: 2.1
Name: pycrystalpay
Version: 0.0.2
Summary: CrystalPay api wrapper
Home-page: https://github.com/mrsmori/pycrystalpay
Author: Lisica
Author-email: nomail@google.com
Classifier: Programming Language :: Python :: 3
Classifier: License :: OSI Approved :: MIT License
Classifier: Operating System :: OS Independent
License-File: LICENSE
Requires-Dist: httpx==0.28.1
Requires-Dist: pydantic==2.10.4
